setup.cfg
setup.py
lalalari/__init__.py
lalalari.egg-info/PKG-INFO
lalalari.egg-info/SOURCES.txt
lalalari.egg-info/dependency_links.txt
lalalari.egg-info/entry_points.txt
lalalari.egg-info/not-zip-safe
lalalari.egg-info/top_level.txt