Metadata-Version: 1.0
Name: lalalari
Version: 0.0.1dev
Summary: llalari es un proyecto de pruebas
Home-page: http://lalari.com
Author: Alejandro Souto
Author-email: sorinaso@gmail.com
License: MIT
Keywords: test
Platform: UNKNOWN
